<?xml version="1.0" encoding="utf-8" ?><dwsync><file name="like.svg" server="ftp.study8center.com/lala/" local="3638737266" remote="3638781900" Dst="-1" /><file name="vaquita1.svg" server="ftp.study8center.com/lala/" local="3638737267" remote="3638781900" Dst="-1" /><file name="plantas.svg" server="ftp.study8center.com/lala/" local="3638737266" remote="3638781900" Dst="-1" /><file name="fabrica.svg" server="ftp.study8center.com/lala/" local="3638737266" remote="3638781900" Dst="-1" /><file name="mexico.svg" server="ftp.study8center.com/lala/" local="3638737266" remote="3638781900" Dst="-1" /><file name="libros.svg" server="ftp.study8center.com/lala/" local="3638737266" remote="3638781900" Dst="-1" /><file name="centroamerica.svg" server="ftp.study8center.com/lala/" local="3638737265" remote="3638781900" Dst="-1" /><file name="brasil.svg" server="ftp.study8center.com/lala/" local="3638737265" remote="3638781900" Dst="-1" /><file name="ventiladores.svg" server="ftp.study8center.com/lala/" local="3638737267" remote="3638781900" Dst="-1" /><file name="trailer1.svg" server="ftp.study8center.com/lala/" local="3638737267" remote="3638781900" Dst="-1" /><file name="verificacion.svg" server="ftp.study8center.com/lala/" local="3638737268" remote="3638781900" Dst="-1" /><file name="trailer2.svg" server="ftp.study8center.com/lala/" local="3638737267" remote="3638781900" Dst="-1" /><file name="eu.svg" server="ftp.study8center.com/lala/" local="3638737266" remote="3638781900" Dst="-1" /><file name="proceso-lala.svg" server="ftp.study8center.com/lala/" local="3638737267" remote="3638781900" Dst="-1" /><file name="leche.svg" server="ftp.study8center.com/lala/" local="3638737266" remote="3638781900" Dst="-1" /><file name="Artboard 1.svg" server="ftp.study8center.com/lala/" local="3638285804" remote="3638781900" Dst="-1" /><file name="proveedores.svg" server="ftp.study8center.com/lala/" local="3638737267" remote="3638781900" Dst="-1" /><file name="fabricas.svg" server="ftp.study8center.com/lala/" local="3638737266" remote="3638781900" Dst="-1" /></dwsync>
